{
  "source_id": "intel-osint",
  "version": 1,
  "entries": [
    {
      "id": "a0",
      "title": "WHY VIRTUAL MACHINES?",
      "level": 1,
      "parent_id": null,
      "start_pdf_page": 9,
      "end_pdf_page": 10,
      "printed_page": "9",
      "confidence": 0.95,
      "source": "anchor_scan"
    },
    {
      "id": "a1",
      "title": "MACOS HOST OPTIMIZATION",
      "level": 1,
      "parent_id": null,
      "start_pdf_page": 11,
      "end_pdf_page": 21,
      "printed_page": "11",
      "confidence": 0.95,
      "source": "anchor_scan"
    },
    {
      "id": "a2",
      "title": "MACOS VM SOFTWARE",
      "level": 1,
      "parent_id": null,
      "start_pdf_page": 22,
      "end_pdf_page": 26,
      "printed_page": "22",
      "confidence": 0.85,
      "source": "anchor_scan"
    },
    {
      "id": "a3",
      "title": "LINUX HOST OPTIMIZATION",
      "level": 1,
      "parent_id": null,
      "start_pdf_page": 27,
      "end_pdf_page": 30,
      "printed_page": "27",
      "confidence": 0.95,
      "source": "anchor_scan"
    },
    {
      "id": "a4",
      "title": "LINUX VM SOFTWARE",
      "level": 1,
      "parent_id": null,
      "start_pdf_page": 31,
      "end_pdf_page": 37,
      "printed_page": "31",
      "confidence": 0.95,
      "source": "anchor_scan"
    },
    {
      "id": "a5",
      "title": "WINDOWS HOST OPTIMIZATION",
      "level": 1,
      "parent_id": null,
      "start_pdf_page": 38,
      "end_pdf_page": 41,
      "printed_page": "38",
      "confidence": 0.95,
      "source": "anchor_scan"
    },
    {
      "id": "a6",
      "title": "WINDOWS VM SOFTWARE",
      "level": 1,
      "parent_id": null,
      "start_pdf_page": 42,
      "end_pdf_page": 48,
      "printed_page": "42",
      "confidence": 0.95,
      "source": "anchor_scan"
    },
    {
      "id": "a7",
      "title": "OSINT VM OPERATING SYSTEMS",
      "level": 1,
      "parent_id": null,
      "start_pdf_page": 49,
      "end_pdf_page": 63,
      "printed_page": "49",
      "confidence": 0.95,
      "source": "anchor_scan"
    },
    {
      "id": "a8",
      "title": "OSINT VM WEB BROWSERS",
      "level": 1,
      "parent_id": null,
      "start_pdf_page": 64,
      "end_pdf_page": 84,
      "printed_page": "64",
      "confidence": 0.95,
      "source": "anchor_scan"
    },
    {
      "id": "a9",
      "title": "OSINT VM APPLICATIONS",
      "level": 1,
      "parent_id": null,
      "start_pdf_page": 85,
      "end_pdf_page": 135,
      "printed_page": "85",
      "confidence": 0.95,
      "source": "anchor_scan"
    },
    {
      "id": "a10",
      "title": "OSINT VM SCRIPTS",
      "level": 1,
      "parent_id": null,
      "start_pdf_page": 136,
      "end_pdf_page": 147,
      "printed_page": "136",
      "confidence": 0.95,
      "source": "anchor_scan"
    },
    {
      "id": "a11",
      "title": "OSINT VM APIS",
      "level": 1,
      "parent_id": null,
      "start_pdf_page": 148,
      "end_pdf_page": 158,
      "printed_page": "148",
      "confidence": 0.95,
      "source": "anchor_scan"
    },
    {
      "id": "a12",
      "title": "OSINT VM MAINTENANCE",
      "level": 1,
      "parent_id": null,
      "start_pdf_page": 159,
      "end_pdf_page": 161,
      "printed_page": "159",
      "confidence": 0.95,
      "source": "anchor_scan"
    },
    {
      "id": "a13",
      "title": "OSINT VM AUTOMATED BUILD",
      "level": 1,
      "parent_id": null,
      "start_pdf_page": 162,
      "end_pdf_page": 162,
      "printed_page": "162",
      "confidence": 0.95,
      "source": "anchor_scan"
    },
    {
      "id": "a14",
      "title": "ANDROID VIRTUALIZATION",
      "level": 1,
      "parent_id": null,
      "start_pdf_page": 163,
      "end_pdf_page": 174,
      "printed_page": "163",
      "confidence": 0.95,
      "source": "anchor_scan"
    },
    {
      "id": "a15",
      "title": "CUSTOM SEARCH TOOLS",
      "level": 1,
      "parent_id": null,
      "start_pdf_page": 175,
      "end_pdf_page": 185,
      "printed_page": "175",
      "confidence": 0.95,
      "source": "anchor_scan"
    },
    {
      "id": "a16",
      "title": "SEARCH ENGINES",
      "level": 1,
      "parent_id": null,
      "start_pdf_page": 186,
      "end_pdf_page": 211,
      "printed_page": "186",
      "confidence": 0.95,
      "source": "anchor_scan"
    },
    {
      "id": "a17",
      "title": "SOCIAL NETWORKS: FACEBOOK",
      "level": 1,
      "parent_id": null,
      "start_pdf_page": 212,
      "end_pdf_page": 227,
      "printed_page": "212",
      "confidence": 0.95,
      "source": "anchor_scan"
    },
    {
      "id": "a18",
      "title": "SOCIAL NETWORKS: X (TWITTER)",
      "level": 1,
      "parent_id": null,
      "start_pdf_page": 228,
      "end_pdf_page": 242,
      "printed_page": "228",
      "confidence": 0.85,
      "source": "anchor_scan"
    },
    {
      "id": "a19",
      "title": "SOCIAL NETWORKS: INSTAGRAM",
      "level": 1,
      "parent_id": null,
      "start_pdf_page": 243,
      "end_pdf_page": 253,
      "printed_page": "243",
      "confidence": 0.95,
      "source": "anchor_scan"
    },
    {
      "id": "a20",
      "title": "SOCIAL NETWORKS: TIKTOK",
      "level": 1,
      "parent_id": null,
      "start_pdf_page": 254,
      "end_pdf_page": 258,
      "printed_page": "254",
      "confidence": 0.95,
      "source": "anchor_scan"
    },
    {
      "id": "a21",
      "title": "ONLINE COMMUNITIES",
      "level": 1,
      "parent_id": null,
      "start_pdf_page": 259,
      "end_pdf_page": 291,
      "printed_page": "259",
      "confidence": 0.95,
      "source": "anchor_scan"
    },
    {
      "id": "a22",
      "title": "EMAIL ADDRESSES",
      "level": 1,
      "parent_id": null,
      "start_pdf_page": 292,
      "end_pdf_page": 302,
      "printed_page": "292",
      "confidence": 0.95,
      "source": "anchor_scan"
    },
    {
      "id": "a23",
      "title": "USERNAMES",
      "level": 1,
      "parent_id": null,
      "start_pdf_page": 303,
      "end_pdf_page": 308,
      "printed_page": "303",
      "confidence": 0.95,
      "source": "anchor_scan"
    },
    {
      "id": "a24",
      "title": "PEOPLE SEARCH ENGINES",
      "level": 1,
      "parent_id": null,
      "start_pdf_page": 309,
      "end_pdf_page": 319,
      "printed_page": "309",
      "confidence": 0.95,
      "source": "anchor_scan"
    },
    {
      "id": "a25",
      "title": "TELEPHONE NUMBERS",
      "level": 1,
      "parent_id": null,
      "start_pdf_page": 320,
      "end_pdf_page": 328,
      "printed_page": "320",
      "confidence": 0.95,
      "source": "anchor_scan"
    },
    {
      "id": "a26",
      "title": "ONLINE MAPS",
      "level": 1,
      "parent_id": null,
      "start_pdf_page": 329,
      "end_pdf_page": 344,
      "printed_page": "329",
      "confidence": 0.95,
      "source": "anchor_scan"
    },
    {
      "id": "a27",
      "title": "DOCUMENTS",
      "level": 1,
      "parent_id": null,
      "start_pdf_page": 345,
      "end_pdf_page": 354,
      "printed_page": "345",
      "confidence": 0.95,
      "source": "anchor_scan"
    },
    {
      "id": "a28",
      "title": "IMAGES",
      "level": 1,
      "parent_id": null,
      "start_pdf_page": 355,
      "end_pdf_page": 371,
      "printed_page": "355",
      "confidence": 0.95,
      "source": "anchor_scan"
    },
    {
      "id": "a29",
      "title": "VIDEOS",
      "level": 1,
      "parent_id": null,
      "start_pdf_page": 372,
      "end_pdf_page": 383,
      "printed_page": "372",
      "confidence": 0.95,
      "source": "anchor_scan"
    },
    {
      "id": "a30",
      "title": "BROADCAST STREAMS",
      "level": 1,
      "parent_id": null,
      "start_pdf_page": 384,
      "end_pdf_page": 395,
      "printed_page": "384",
      "confidence": 0.95,
      "source": "anchor_scan"
    },
    {
      "id": "a31",
      "title": "DOMAIN NAMES",
      "level": 1,
      "parent_id": null,
      "start_pdf_page": 396,
      "end_pdf_page": 415,
      "printed_page": "396",
      "confidence": 0.95,
      "source": "anchor_scan"
    },
    {
      "id": "a32",
      "title": "IP ADDRESSES",
      "level": 1,
      "parent_id": null,
      "start_pdf_page": 416,
      "end_pdf_page": 423,
      "printed_page": "416",
      "confidence": 0.95,
      "source": "anchor_scan"
    },
    {
      "id": "a33",
      "title": "GOVERNMENT & BUSINESS RECORDS",
      "level": 1,
      "parent_id": null,
      "start_pdf_page": 424,
      "end_pdf_page": 432,
      "printed_page": "424",
      "confidence": 0.95,
      "source": "anchor_scan"
    },
    {
      "id": "a34",
      "title": "VIRTUAL CURRENCIES",
      "level": 1,
      "parent_id": null,
      "start_pdf_page": 433,
      "end_pdf_page": 437,
      "printed_page": "433",
      "confidence": 0.95,
      "source": "anchor_scan"
    },
    {
      "id": "a35",
      "title": "BREACHES: INVESTIGATIVE BENEFITS",
      "level": 1,
      "parent_id": null,
      "start_pdf_page": 438,
      "end_pdf_page": 439,
      "printed_page": "438",
      "confidence": 0.5,
      "source": "anchor_scan"
    },
    {
      "id": "a36",
      "title": "BREACHES: HARDWARE CONFIGURATION",
      "level": 1,
      "parent_id": null,
      "start_pdf_page": 440,
      "end_pdf_page": 444,
      "printed_page": "440",
      "confidence": 0.5,
      "source": "anchor_scan"
    },
    {
      "id": "a37",
      "title": "BREACHES: SOFTWARE CONFIGURATION",
      "level": 1,
      "parent_id": null,
      "start_pdf_page": 445,
      "end_pdf_page": 458,
      "printed_page": "445",
      "confidence": 0.85,
      "source": "anchor_scan"
    },
    {
      "id": "a38",
      "title": "BREACHES: TERMINAL COMMANDS",
      "level": 1,
      "parent_id": null,
      "start_pdf_page": 459,
      "end_pdf_page": 470,
      "printed_page": "459",
      "confidence": 0.5,
      "source": "anchor_scan"
    },
    {
      "id": "a39",
      "title": "DATA LEAKS",
      "level": 1,
      "parent_id": null,
      "start_pdf_page": 471,
      "end_pdf_page": 494,
      "printed_page": "471",
      "confidence": 0.95,
      "source": "anchor_scan"
    },
    {
      "id": "a40",
      "title": "DATA BREACHES",
      "level": 1,
      "parent_id": null,
      "start_pdf_page": 495,
      "end_pdf_page": 517,
      "printed_page": "495",
      "confidence": 0.95,
      "source": "anchor_scan"
    },
    {
      "id": "a41",
      "title": "STEALER LOGS",
      "level": 1,
      "parent_id": null,
      "start_pdf_page": 518,
      "end_pdf_page": 533,
      "printed_page": "518",
      "confidence": 0.95,
      "source": "anchor_scan"
    },
    {
      "id": "a42",
      "title": "RANSOMWARE",
      "level": 1,
      "parent_id": null,
      "start_pdf_page": 534,
      "end_pdf_page": 538,
      "printed_page": "534",
      "confidence": 0.95,
      "source": "anchor_scan"
    },
    {
      "id": "a43",
      "title": "QUERIES, SCRIPTS, DATABASES, & BACKUPS",
      "level": 1,
      "parent_id": null,
      "start_pdf_page": 539,
      "end_pdf_page": 560,
      "printed_page": "539",
      "confidence": 0.95,
      "source": "anchor_scan"
    },
    {
      "id": "a44",
      "title": "METHODOLOGY & WORKFLOW",
      "level": 1,
      "parent_id": null,
      "start_pdf_page": 561,
      "end_pdf_page": 571,
      "printed_page": "561",
      "confidence": 0.95,
      "source": "anchor_scan"
    },
    {
      "id": "a45",
      "title": "DOCUMENTATION & REPORTING",
      "level": 1,
      "parent_id": null,
      "start_pdf_page": 572,
      "end_pdf_page": 581,
      "printed_page": "572",
      "confidence": 0.95,
      "source": "anchor_scan"
    },
    {
      "id": "a46",
      "title": "POLICY, ETHICS, & DEVELOPMENT",
      "level": 1,
      "parent_id": null,
      "start_pdf_page": 582,
      "end_pdf_page": 590,
      "printed_page": "582",
      "confidence": 0.95,
      "source": "anchor_scan"
    }
  ]
}